{
  "items": [
    {
      "_attributes": {
        "termsofuse": "https://boardgamegeek.com/xmlapi/termsofuse"
      },
      "item": [
        {
          "_attributes": {
            "type": "boardgameexpansion",
            "id": "147101"
          },
          "thumbnail": [
            {
              "_text": [
                "https://cf.geekdo-images.com/thumb/img/Cca-nVhHrCluIsQ35YQeSDbq-u4=/fit-in/200x150/pic1886437.jpg"
              ]
            }
          ],
          "image": [
            {
              "_text": [
                "https://cf.geekdo-images.com/original/img/4W5_SWLSqYrtb4MVSaHO8mWX2M8=/0x0/pic1886437.jpg"
              ]
            }
          ],
          "name": [
            {
              "_attributes": {
                "type": "primary",
                "sortindex": "1",
                "value": "Viticulture: Tuscany – Expand the World of Viticulture"
              }
            },
            {
              "_attributes": {
                "type": "alternate",
                "sortindex": "1",
                "value": "Viticulture: Tuscany"
              }
            },
            {
              "_attributes": {
                "type": "alternate",
                "sortindex": "1",
                "value": "ワイナリーの四季: トスカーナ"
              }
            }
          ],
          "description": [
            {
              "_text": [
                "Tuscany: Expand the World of Viticulture significantly extends the original game of winemaking. Using a tiered system that lets you gradually unlock (&quot;uncork&quot;) a number of new expansions to Viticulture legacy-style in an order that's unique to your game, Tuscany enhances and completes the rustic world that Viticulture introduced. Just like Viticulture, Tuscany plays 2-6 players and has a play time of around 20 minutes per player.&#10;&#10;These expansions add asymmetric starting resources, new and advanced visitor cards, an extended game board for actions in all four seasons, special types of worker meeples, and more. What story will you tell as you seek to create the most successful vineyard in Tuscany?&#10;&#10;"
              ]
            }
          ],
          "yearpublished": [
            {
              "_attributes": {
                "value": "2014"
              }
            }
          ],
          "minplayers": [
            {
              "_attributes": {
                "value": "1"
              }
            }
          ],
          "maxplayers": [
            {
              "_attributes": {
                "value": "6"
              }
            }
          ],
          "poll": [
            {
              "_attributes": {
                "name": "suggested_numplayers",
                "title": "User Suggested Number of Players",
                "totalvotes": "34"
              },
              "results": [
                {
                  "_attributes": {
                    "numplayers": "1"
                  },
                  "result": [
                    {
                      "_attributes": {
                        "value": "Best",
                        "numvotes": "6"
                      }
                    },
                    {
                      "_attributes": {
                        "value": "Recommended",
                        "numvotes": "12"
                      }
                    },
                    {
                      "_attributes": {
                        "value": "Not Recommended",
                        "numvotes": "2"
                      }
                    }
                  ]
                },
                {
                  "_attributes": {
                    "numplayers": "2"
                  },
                  "result": [
                    {
                      "_attributes": {
                        "value": "Best",
                        "numvotes": "7"
                      }
                    },
                    {
                      "_attributes": {
                        "value": "Recommended",
                        "numvotes": "15"
                      }
                    },
                    {
                      "_attributes": {
                        "value": "Not Recommended",
                        "numvotes": "0"
                      }
                    }
                  ]
                },
                {
                  "_attributes": {
                    "numplayers": "3"
                  },
                  "result": [
                    {
                      "_attributes": {
                        "value": "Best",
                        "numvotes": "12"
                      }
                    },
                    {
                      "_attributes": {
                        "value": "Recommended",
                        "numvotes": "13"
                      }
                    },
                    {
                      "_attributes": {
                        "value": "Not Recommended",
                        "numvotes": "0"
                      }
                    }
                  ]
                },
                {
                  "_attributes": {
                    "numplayers": "4"
                  },
                  "result": [
                    {
                      "_attributes": {
                        "value": "Best",
                        "numvotes": "19"
                      }
                    },
                    {
                      "_attributes": {
                        "value": "Recommended",
                        "numvotes": "9"
                      }
                    },
                    {
                      "_attributes": {
                        "value": "Not Recommended",
                        "numvotes": "0"
                      }
                    }
                  ]
                },
                {
                  "_attributes": {
                    "numplayers": "5"
                  },
                  "result": [
                    {
                      "_attributes": {
                        "value": "Best",
                        "numvotes": "6"
                      }
                    },
                    {
                      "_attributes": {
                        "value": "Recommended",
                        "numvotes": "12"
                      }
                    },
                    {
                      "_attributes": {
                        "value": "Not Recommended",
                        "numvotes": "3"
                      }
                    }
                  ]
                },
                {
                  "_attributes": {
                    "numplayers": "6"
                  },
                  "result": [
                    {
                      "_attributes": {
                        "value": "Best",
                        "numvotes": "2"
                      }
                    },
                    {
                      "_attributes": {
                        "value": "Recommended",
                        "numvotes": "10"
                      }
                    },
                    {
                      "_attributes": {
                        "value": "Not Recommended",
                        "numvotes": "8"
                      }
                    }
                  ]
                },
                {
                  "_attributes": {
                    "numplayers": "6+"
                  },
                  "result": [
                    {
                      "_attributes": {
                        "value": "Best",
                        "numvotes": "0"
                      }
                    },
                    {
                      "_attributes": {
                        "value": "Recommended",
                        "numvotes": "0"
                      }
                    },
                    {
                      "_attributes": {
                        "value": "Not Recommended",
                        "numvotes": "13"
                      }
                    }
                  ]
                }
              ]
            },
            {
              "_attributes": {
                "name": "suggested_playerage",
                "title": "User Suggested Player Age",
                "totalvotes": "9"
              },
              "results": [
                {
                  "result": [
                    {
                      "_attributes": {
                        "value": "2",
                        "numvotes": "0"
                      }
                    },
                    {
                      "_attributes": {
                        "value": "3",
                        "numvotes": "0"
                      }
                    },
                    {
                      "_attributes": {
                        "value": "4",
                        "numvotes": "0"
                      }
                    },
                    {
                      "_attributes": {
                        "value": "5",
                        "numvotes": "0"
                      }
                    },
                    {
                      "_attributes": {
                        "value": "6",
                        "numvotes": "0"
                      }
                    },
                    {
                      "_attributes": {
                        "value": "8",
                        "numvotes": "0"
                      }
                    },
                    {
                      "_attributes": {
                        "value": "10",
                        "numvotes": "2"
                      }
                    },
                    {
                      "_attributes": {
                        "value": "12",
                        "numvotes": "5"
                      }
                    },
                    {
                      "_attributes": {
                        "value": "14",
                        "numvotes": "2"
                      }
                    },
                    {
                      "_attributes": {
                        "value": "16",
                        "numvotes": "0"
                      }
                    },
                    {
                      "_attributes": {
                        "value": "18",
                        "numvotes": "0"
                      }
                    },
                    {
                      "_attributes": {
                        "value": "21 and up",
                        "numvotes": "0"
                      }
                    }
                  ]
                }
              ]
            },
            {
              "_attributes": {
                "name": "language_dependence",
                "title": "Language Dependence",
                "totalvotes": "11"
              },
              "results": [
                {
                  "result": [
                    {
                      "_attributes": {
                        "level": "6",
                        "value": "No necessary in-game text",
                        "numvotes": "0"
                      }
                    },
                    {
                      "_attributes": {
                        "level": "7",
                        "value": "Some necessary text - easily memorized or small crib sheet",
                        "numvotes": "1"
                      }
                    },
                    {
                      "_attributes": {
                        "level": "8",
                        "value": "Moderate in-game text - needs crib sheet or paste ups",
                        "numvotes": "7"
                      }
                    },
                    {
                      "_attributes": {
                        "level": "9",
                        "value": "Extensive use of text - massive conversion needed to be playable",
                        "numvotes": "2"
                      }
                    },
                    {
                      "_attributes": {
                        "level": "10",
                        "value": "Unplayable in another language",
                        "numvotes": "1"
                      }
                    }
                  ]
                }
              ]
            }
          ],
          "playingtime": [
            {
              "_attributes": {
                "value": "120"
              }
            }
          ],
          "minplaytime": [
            {
              "_attributes": {
                "value": "60"
              }
            }
          ],
          "maxplaytime": [
            {
              "_attributes": {
                "value": "120"
              }
            }
          ],
          "minage": [
            {
              "_attributes": {
                "value": "14"
              }
            }
          ],
          "link": [
            {
              "_attributes": {
                "type": "boardgamecategory",
                "id": "1042",
                "value": "Expansion for Base-game"
              }
            },
            {
              "_attributes": {
                "type": "boardgamecategory",
                "id": "1013",
                "value": "Farming"
              }
            },
            {
              "_attributes": {
                "type": "boardgamemechanic",
                "id": "2015",
                "value": "Variable Player Powers"
              }
            },
            {
              "_attributes": {
                "type": "boardgamemechanic",
                "id": "2082",
                "value": "Worker Placement"
              }
            },
            {
              "_attributes": {
                "type": "boardgamefamily",
                "id": "8374",
                "value": "Crowdfunding: Kickstarter"
              }
            },
            {
              "_attributes": {
                "type": "boardgamefamily",
                "id": "8496",
                "value": "Theme: Wine"
              }
            },
            {
              "_attributes": {
                "type": "boardgamefamily",
                "id": "23988",
                "value": "Viticulture"
              }
            },
            {
              "_attributes": {
                "type": "boardgameexpansion",
                "id": "256549",
                "value": "Tuscany & Euphoria Crossover structures"
              }
            },
            {
              "_attributes": {
                "type": "boardgameexpansion",
                "id": "214463",
                "value": "Tuscany: Special Worker Promo Cards"
              }
            },
            {
              "_attributes": {
                "type": "boardgameexpansion",
                "id": "128621",
                "value": "Viticulture",
                "inbound": "true"
              }
            },
            {
              "_attributes": {
                "type": "boardgamecompilation",
                "id": "130655",
                "value": "Viticulture: Arboriculture Expansion",
                "inbound": "true"
              }
            },
            {
              "_attributes": {
                "type": "boardgamecompilation",
                "id": "140045",
                "value": "Viticulture: Kickstarter Promotional Cards",
                "inbound": "true"
              }
            },
            {
              "_attributes": {
                "type": "boardgamecompilation",
                "id": "156455",
                "value": "Viticulture: Complete Collector's Edition"
              }
            },
            {
              "_attributes": {
                "type": "boardgameimplementation",
                "id": "202174",
                "value": "Viticulture: Tuscany Essential Edition"
              }
            },
            {
              "_attributes": {
                "type": "boardgamedesigner",
                "id": "71006",
                "value": "Morten Monrad Pedersen"
              }
            },
            {
              "_attributes": {
                "type": "boardgamedesigner",
                "id": "62640",
                "value": "Jamey Stegmaier"
              }
            },
            {
              "_attributes": {
                "type": "boardgamedesigner",
                "id": "62641",
                "value": "Alan Stone"
              }
            },
            {
              "_attributes": {
                "type": "boardgameartist",
                "id": "71006",
                "value": "Morten Monrad Pedersen"
              }
            },
            {
              "_attributes": {
                "type": "boardgameartist",
                "id": "71164",
                "value": "Beth Sobel"
              }
            },
            {
              "_attributes": {
                "type": "boardgameartist",
                "id": "62640",
                "value": "Jamey Stegmaier"
              }
            },
            {
              "_attributes": {
                "type": "boardgameartist",
                "id": "62641",
                "value": "Alan Stone"
              }
            },
            {
              "_attributes": {
                "type": "boardgamepublisher",
                "id": "3475",
                "value": "Arclight"
              }
            },
            {
              "_attributes": {
                "type": "boardgamepublisher",
                "id": "1391",
                "value": "Hobby Japan"
              }
            },
            {
              "_attributes": {
                "type": "boardgamepublisher",
                "id": "30677",
                "value": "Maldito Games"
              }
            },
            {
              "_attributes": {
                "type": "boardgamepublisher",
                "id": "23202",
                "value": "Stonemaier Games"
              }
            }
          ],
          "statistics": [
            {
              "_attributes": {
                "page": "1"
              },
              "ratings": [
                {
                  "usersrated": [
                    {
                      "_attributes": {
                        "value": "2373"
                      }
                    }
                  ],
                  "average": [
                    {
                      "_attributes": {
                        "value": "8.44278"
                      }
                    }
                  ],
                  "bayesaverage": [
                    {
                      "_attributes": {
                        "value": "7.32529"
                      }
                    }
                  ],
                  "ranks": [
                    {
                      "rank": [
                        {
                          "_attributes": {
                            "type": "subtype",
                            "id": "1",
                            "name": "boardgame",
                            "friendlyname": "Board Game Rank",
                            "value": "Not Ranked",
                            "bayesaverage": "7.32529"
                          }
                        },
                        {
                          "_attributes": {
                            "type": "family",
                            "id": "5497",
                            "name": "strategygames",
                            "friendlyname": "Strategy Game Rank",
                            "value": "Not Ranked",
                            "bayesaverage": "7.55664"
                          }
                        }
                      ]
                    }
                  ],
                  "stddev": [
                    {
                      "_attributes": {
                        "value": "1.23025"
                      }
                    }
                  ],
                  "median": [
                    {
                      "_attributes": {
                        "value": "0"
                      }
                    }
                  ],
                  "owned": [
                    {
                      "_attributes": {
                        "value": "5896"
                      }
                    }
                  ],
                  "trading": [
                    {
                      "_attributes": {
                        "value": "49"
                      }
                    }
                  ],
                  "wanting": [
                    {
                      "_attributes": {
                        "value": "124"
                      }
                    }
                  ],
                  "wishing": [
                    {
                      "_attributes": {
                        "value": "485"
                      }
                    }
                  ],
                  "numcomments": [
                    {
                      "_attributes": {
                        "value": "554"
                      }
                    }
                  ],
                  "numweights": [
                    {
                      "_attributes": {
                        "value": "110"
                      }
                    }
                  ],
                  "averageweight": [
                    {
                      "_attributes": {
                        "value": "3.3909"
                      }
                    }
                  ]
                }
              ]
            }
          ]
        }
      ]
    }
  ]
}