{
  "items": [
    {
      "_attributes": {
        "termsofuse": "https://boardgamegeek.com/xmlapi/termsofuse"
      },
      "item": [
        {
          "_attributes": {
            "type": "boardgame",
            "id": "276894"
          },
          "thumbnail": [
            {
              "_text": [
                "https://cf.geekdo-images.com/thumb/img/4mf7t9pBw-pkxlFLBFmRi8Qswks=/fit-in/200x150/pic4666620.png"
              ]
            }
          ],
          "image": [
            {
              "_text": [
                "https://cf.geekdo-images.com/original/img/KoyAccblPb-aiGeGvnNJmcqgRMk=/0x0/pic4666620.png"
              ]
            }
          ],
          "name": [
            {
              "_attributes": {
                "type": "primary",
                "sortindex": "1",
                "value": "Ticket to Ride: London"
              }
            },
            {
              "_attributes": {
                "type": "alternate",
                "sortindex": "5",
                "value": "Les Aventuriers du Rail: Londres"
              }
            },
            {
              "_attributes": {
                "type": "alternate",
                "sortindex": "1",
                "value": "Ticket to Ride: Londra"
              }
            },
            {
              "_attributes": {
                "type": "alternate",
                "sortindex": "1",
                "value": "Ticket to Ride: Londres"
              }
            },
            {
              "_attributes": {
                "type": "alternate",
                "sortindex": "1",
                "value": "Wsiąść do Pociągu: Londyn"
              }
            },
            {
              "_attributes": {
                "type": "alternate",
                "sortindex": "1",
                "value": "Zug um Zug: London"
              }
            },
            {
              "_attributes": {
                "type": "alternate",
                "sortindex": "1",
                "value": "チケット・トゥ・ライド: ロンドン"
              }
            }
          ],
          "description": [
            {
              "_text": [
                "Ticket to Ride: London features the familiar gameplay from the Ticket to Ride game series &mdash; collect cards, claim routes, draw tickets &mdash; but on a scaled-down map of 1970s London that allows you to complete a game in no more than 15 minutes.&#10;&#10;Each player starts with a supply of 17 double-decker buses, two transportation cards in hand, and one or two destination tickets that show locations in London. On a turn, you either draw two transportation cards from the deck or the display of five face-up cards (or you take one face-up bus, which counts as all six colors in the game); or you claim a route on the board by discarding cards that match the color of the route being claimed (with any set of cards allowing you to claim a gray route); or you draw two destination tickets and keep at least one of them.&#10;&#10;Players take turns until someone has no more than two buses in their supply, then each player takes one final turn, including the player who triggered the end of the game. Players then sum their points, scoring points for (1) the routes that they've claimed during the game, (2) the destination tickets that they've completed (by connecting the two locations on a ticket by a continuous line of their buses), and (3) the districts that they've connected. (A district consists of 2-4 locations, and you score 1-5 points for a district if you link all of its locations to one another with your buses.) You lose points for any uncompleted destination tickets, then whoever has the high score wins!&#10;&#10;"
              ]
            }
          ],
          "yearpublished": [
            {
              "_attributes": {
                "value": "2019"
              }
            }
          ],
          "minplayers": [
            {
              "_attributes": {
                "value": "2"
              }
            }
          ],
          "maxplayers": [
            {
              "_attributes": {
                "value": "4"
              }
            }
          ],
          "poll": [
            {
              "_attributes": {
                "name": "suggested_numplayers",
                "title": "User Suggested Number of Players",
                "totalvotes": "11"
              },
              "results": [
                {
                  "_attributes": {
                    "numplayers": "1"
                  },
                  "result": [
                    {
                      "_attributes": {
                        "value": "Best",
                        "numvotes": "0"
                      }
                    },
                    {
                      "_attributes": {
                        "value": "Recommended",
                        "numvotes": "0"
                      }
                    },
                    {
                      "_attributes": {
                        "value": "Not Recommended",
                        "numvotes": "7"
                      }
                    }
                  ]
                },
                {
                  "_attributes": {
                    "numplayers": "2"
                  },
                  "result": [
                    {
                      "_attributes": {
                        "value": "Best",
                        "numvotes": "2"
                      }
                    },
                    {
                      "_attributes": {
                        "value": "Recommended",
                        "numvotes": "7"
                      }
                    },
                    {
                      "_attributes": {
                        "value": "Not Recommended",
                        "numvotes": "1"
                      }
                    }
                  ]
                },
                {
                  "_attributes": {
                    "numplayers": "3"
                  },
                  "result": [
                    {
                      "_attributes": {
                        "value": "Best",
                        "numvotes": "8"
                      }
                    },
                    {
                      "_attributes": {
                        "value": "Recommended",
                        "numvotes": "3"
                      }
                    },
                    {
                      "_attributes": {
                        "value": "Not Recommended",
                        "numvotes": "0"
                      }
                    }
                  ]
                },
                {
                  "_attributes": {
                    "numplayers": "4"
                  },
                  "result": [
                    {
                      "_attributes": {
                        "value": "Best",
                        "numvotes": "4"
                      }
                    },
                    {
                      "_attributes": {
                        "value": "Recommended",
                        "numvotes": "6"
                      }
                    },
                    {
                      "_attributes": {
                        "value": "Not Recommended",
                        "numvotes": "0"
                      }
                    }
                  ]
                },
                {
                  "_attributes": {
                    "numplayers": "4+"
                  },
                  "result": [
                    {
                      "_attributes": {
                        "value": "Best",
                        "numvotes": "0"
                      }
                    },
                    {
                      "_attributes": {
                        "value": "Recommended",
                        "numvotes": "0"
                      }
                    },
                    {
                      "_attributes": {
                        "value": "Not Recommended",
                        "numvotes": "5"
                      }
                    }
                  ]
                }
              ]
            },
            {
              "_attributes": {
                "name": "suggested_playerage",
                "title": "User Suggested Player Age",
                "totalvotes": "7"
              },
              "results": [
                {
                  "result": [
                    {
                      "_attributes": {
                        "value": "2",
                        "numvotes": "0"
                      }
                    },
                    {
                      "_attributes": {
                        "value": "3",
                        "numvotes": "0"
                      }
                    },
                    {
                      "_attributes": {
                        "value": "4",
                        "numvotes": "0"
                      }
                    },
                    {
                      "_attributes": {
                        "value": "5",
                        "numvotes": "0"
                      }
                    },
                    {
                      "_attributes": {
                        "value": "6",
                        "numvotes": "3"
                      }
                    },
                    {
                      "_attributes": {
                        "value": "8",
                        "numvotes": "4"
                      }
                    },
                    {
                      "_attributes": {
                        "value": "10",
                        "numvotes": "0"
                      }
                    },
                    {
                      "_attributes": {
                        "value": "12",
                        "numvotes": "0"
                      }
                    },
                    {
                      "_attributes": {
                        "value": "14",
                        "numvotes": "0"
                      }
                    },
                    {
                      "_attributes": {
                        "value": "16",
                        "numvotes": "0"
                      }
                    },
                    {
                      "_attributes": {
                        "value": "18",
                        "numvotes": "0"
                      }
                    },
                    {
                      "_attributes": {
                        "value": "21 and up",
                        "numvotes": "0"
                      }
                    }
                  ]
                }
              ]
            },
            {
              "_attributes": {
                "name": "language_dependence",
                "title": "Language Dependence",
                "totalvotes": "4"
              },
              "results": [
                {
                  "result": [
                    {
                      "_attributes": {
                        "level": "26",
                        "value": "No necessary in-game text",
                        "numvotes": "4"
                      }
                    },
                    {
                      "_attributes": {
                        "level": "27",
                        "value": "Some necessary text - easily memorized or small crib sheet",
                        "numvotes": "0"
                      }
                    },
                    {
                      "_attributes": {
                        "level": "28",
                        "value": "Moderate in-game text - needs crib sheet or paste ups",
                        "numvotes": "0"
                      }
                    },
                    {
                      "_attributes": {
                        "level": "29",
                        "value": "Extensive use of text - massive conversion needed to be playable",
                        "numvotes": "0"
                      }
                    },
                    {
                      "_attributes": {
                        "level": "30",
                        "value": "Unplayable in another language",
                        "numvotes": "0"
                      }
                    }
                  ]
                }
              ]
            }
          ],
          "playingtime": [
            {
              "_attributes": {
                "value": "15"
              }
            }
          ],
          "minplaytime": [
            {
              "_attributes": {
                "value": "10"
              }
            }
          ],
          "maxplaytime": [
            {
              "_attributes": {
                "value": "15"
              }
            }
          ],
          "minage": [
            {
              "_attributes": {
                "value": "8"
              }
            }
          ],
          "link": [
            {
              "_attributes": {
                "type": "boardgamecategory",
                "id": "1034",
                "value": "Trains"
              }
            },
            {
              "_attributes": {
                "type": "boardgamemechanic",
                "id": "2041",
                "value": "Card Drafting"
              }
            },
            {
              "_attributes": {
                "type": "boardgamemechanic",
                "id": "2040",
                "value": "Hand Management"
              }
            },
            {
              "_attributes": {
                "type": "boardgamemechanic",
                "id": "2081",
                "value": "Network and Route Building"
              }
            },
            {
              "_attributes": {
                "type": "boardgamemechanic",
                "id": "2004",
                "value": "Set Collection"
              }
            },
            {
              "_attributes": {
                "type": "boardgamefamily",
                "id": "17446",
                "value": "Cities: London (England)"
              }
            },
            {
              "_attributes": {
                "type": "boardgamefamily",
                "id": "17",
                "value": "Ticket to Ride"
              }
            },
            {
              "_attributes": {
                "type": "boardgameimplementation",
                "id": "9209",
                "value": "Ticket to Ride",
                "inbound": "true"
              }
            },
            {
              "_attributes": {
                "type": "boardgamedesigner",
                "id": "9",
                "value": "Alan R. Moon"
              }
            },
            {
              "_attributes": {
                "type": "boardgameartist",
                "id": "12519",
                "value": "Cyrille Daujean"
              }
            },
            {
              "_attributes": {
                "type": "boardgameartist",
                "id": "11886",
                "value": "Julien Delval"
              }
            },
            {
              "_attributes": {
                "type": "boardgamepublisher",
                "id": "1027",
                "value": "Days of Wonder"
              }
            },
            {
              "_attributes": {
                "type": "boardgamepublisher",
                "id": "15605",
                "value": "Galápagos Jogos"
              }
            }
          ],
          "statistics": [
            {
              "_attributes": {
                "page": "1"
              },
              "ratings": [
                {
                  "usersrated": [
                    {
                      "_attributes": {
                        "value": "807"
                      }
                    }
                  ],
                  "average": [
                    {
                      "_attributes": {
                        "value": "7.34385"
                      }
                    }
                  ],
                  "bayesaverage": [
                    {
                      "_attributes": {
                        "value": "6.17212"
                      }
                    }
                  ],
                  "ranks": [
                    {
                      "rank": [
                        {
                          "_attributes": {
                            "type": "subtype",
                            "id": "1",
                            "name": "boardgame",
                            "friendlyname": "Board Game Rank",
                            "value": "1713",
                            "bayesaverage": "6.17212"
                          }
                        },
                        {
                          "_attributes": {
                            "type": "family",
                            "id": "5499",
                            "name": "familygames",
                            "friendlyname": "Family Game Rank",
                            "value": "395",
                            "bayesaverage": "6.36193"
                          }
                        }
                      ]
                    }
                  ],
                  "stddev": [
                    {
                      "_attributes": {
                        "value": "1.10576"
                      }
                    }
                  ],
                  "median": [
                    {
                      "_attributes": {
                        "value": "0"
                      }
                    }
                  ],
                  "owned": [
                    {
                      "_attributes": {
                        "value": "2203"
                      }
                    }
                  ],
                  "trading": [
                    {
                      "_attributes": {
                        "value": "8"
                      }
                    }
                  ],
                  "wanting": [
                    {
                      "_attributes": {
                        "value": "65"
                      }
                    }
                  ],
                  "wishing": [
                    {
                      "_attributes": {
                        "value": "360"
                      }
                    }
                  ],
                  "numcomments": [
                    {
                      "_attributes": {
                        "value": "189"
                      }
                    }
                  ],
                  "numweights": [
                    {
                      "_attributes": {
                        "value": "17"
                      }
                    }
                  ],
                  "averageweight": [
                    {
                      "_attributes": {
                        "value": "1.1765"
                      }
                    }
                  ]
                }
              ]
            }
          ]
        }
      ]
    }
  ]
}