{
  "items": [
    {
      "_attributes": {
        "termsofuse": "https://boardgamegeek.com/xmlapi/termsofuse"
      },
      "item": [
        {
          "_attributes": {
            "type": "boardgameexpansion",
            "id": "147938"
          },
          "thumbnail": [
            {
              "_text": [
                "https://cf.geekdo-images.com/thumb/img/a1Cv-HJKukMsXYwhnkehIUUdkjU=/fit-in/200x150/pic1777274.jpg"
              ]
            }
          ],
          "image": [
            {
              "_text": [
                "https://cf.geekdo-images.com/original/img/CpDyx_FPGd-DUaccLZqLKLh0buE=/0x0/pic1777274.jpg"
              ]
            }
          ],
          "name": [
            {
              "_attributes": {
                "type": "primary",
                "sortindex": "1",
                "value": "Ticket to Ride Map Collection: Volume 4 – Nederland"
              }
            },
            {
              "_attributes": {
                "type": "alternate",
                "sortindex": "5",
                "value": "Les aventuriers du rail: Pays-Bas"
              }
            },
            {
              "_attributes": {
                "type": "alternate",
                "sortindex": "1",
                "value": "Wsiąść do Pociągu: Holandia"
              }
            },
            {
              "_attributes": {
                "type": "alternate",
                "sortindex": "1",
                "value": "Zug um Zug: Erweiterung 4 – Niederlande"
              }
            }
          ],
          "description": [
            {
              "_text": [
                "Ticket to Ride Map Collection: Volume 4 - Nederland contains a new game board with new rules for use with Ticket to Ride or Ticket to Ride: Europe with players now creating train lines in the Netherlands.&#10;&#10;The basics of TtR gameplay remain the same as always &mdash; players collect train cards in order to claim routes between pairs of cities with the overall goal of completing tickets they hold in hand &mdash; but Ticket to Ride: Nederland twists this gameplay in two ways. First, nearly every route on the game board is a double-route, with two tracks connecting cities. Both of these routes are in play no matter how many players are in the game.&#10;&#10;Second, every route &mdash; whether double or single &mdash; has a bridge toll that a player must pay when building on that route. On a single route or the first track of a double route, the player pays this toll &mdash; which costs 1-4 coins &mdash; to the bank; on the second track of a double route, the player pays this toll to the player who built the first track. Players start the game with 30 coins, and if you can't pay a toll, you must take a loan card to cover the fare, with each loan costing you 5 points at the end of the game.&#10;&#10;In addition to helping you avoid loans, coins matter because at game's end, players receive a bonus based on how many coins they hold relative to everyone else. In a five-player game, for example, the player with the most coins scores a 55 point bonus; the 2nd place player scores 35 points, and the other players 20, 10 and 0 points. If you've taken a loan, however, you're ineligible for this bonus scoring, so players have an incentive to build early and often.&#10;&#10;These coin bonuses are balanced by the multitude of destination tickets with large point values: six of them are worth 29+ points while another seventeen are worth 17-26 points.&#10;&#10;"
              ]
            }
          ],
          "yearpublished": [
            {
              "_attributes": {
                "value": "2013"
              }
            }
          ],
          "minplayers": [
            {
              "_attributes": {
                "value": "2"
              }
            }
          ],
          "maxplayers": [
            {
              "_attributes": {
                "value": "5"
              }
            }
          ],
          "poll": [
            {
              "_attributes": {
                "name": "suggested_numplayers",
                "title": "User Suggested Number of Players",
                "totalvotes": "30"
              },
              "results": [
                {
                  "_attributes": {
                    "numplayers": "1"
                  },
                  "result": [
                    {
                      "_attributes": {
                        "value": "Best",
                        "numvotes": "0"
                      }
                    },
                    {
                      "_attributes": {
                        "value": "Recommended",
                        "numvotes": "0"
                      }
                    },
                    {
                      "_attributes": {
                        "value": "Not Recommended",
                        "numvotes": "18"
                      }
                    }
                  ]
                },
                {
                  "_attributes": {
                    "numplayers": "2"
                  },
                  "result": [
                    {
                      "_attributes": {
                        "value": "Best",
                        "numvotes": "2"
                      }
                    },
                    {
                      "_attributes": {
                        "value": "Recommended",
                        "numvotes": "8"
                      }
                    },
                    {
                      "_attributes": {
                        "value": "Not Recommended",
                        "numvotes": "12"
                      }
                    }
                  ]
                },
                {
                  "_attributes": {
                    "numplayers": "3"
                  },
                  "result": [
                    {
                      "_attributes": {
                        "value": "Best",
                        "numvotes": "6"
                      }
                    },
                    {
                      "_attributes": {
                        "value": "Recommended",
                        "numvotes": "13"
                      }
                    },
                    {
                      "_attributes": {
                        "value": "Not Recommended",
                        "numvotes": "4"
                      }
                    }
                  ]
                },
                {
                  "_attributes": {
                    "numplayers": "4"
                  },
                  "result": [
                    {
                      "_attributes": {
                        "value": "Best",
                        "numvotes": "19"
                      }
                    },
                    {
                      "_attributes": {
                        "value": "Recommended",
                        "numvotes": "6"
                      }
                    },
                    {
                      "_attributes": {
                        "value": "Not Recommended",
                        "numvotes": "0"
                      }
                    }
                  ]
                },
                {
                  "_attributes": {
                    "numplayers": "5"
                  },
                  "result": [
                    {
                      "_attributes": {
                        "value": "Best",
                        "numvotes": "15"
                      }
                    },
                    {
                      "_attributes": {
                        "value": "Recommended",
                        "numvotes": "7"
                      }
                    },
                    {
                      "_attributes": {
                        "value": "Not Recommended",
                        "numvotes": "2"
                      }
                    }
                  ]
                },
                {
                  "_attributes": {
                    "numplayers": "5+"
                  },
                  "result": [
                    {
                      "_attributes": {
                        "value": "Best",
                        "numvotes": "0"
                      }
                    },
                    {
                      "_attributes": {
                        "value": "Recommended",
                        "numvotes": "0"
                      }
                    },
                    {
                      "_attributes": {
                        "value": "Not Recommended",
                        "numvotes": "10"
                      }
                    }
                  ]
                }
              ]
            },
            {
              "_attributes": {
                "name": "suggested_playerage",
                "title": "User Suggested Player Age",
                "totalvotes": "9"
              },
              "results": [
                {
                  "result": [
                    {
                      "_attributes": {
                        "value": "2",
                        "numvotes": "0"
                      }
                    },
                    {
                      "_attributes": {
                        "value": "3",
                        "numvotes": "0"
                      }
                    },
                    {
                      "_attributes": {
                        "value": "4",
                        "numvotes": "0"
                      }
                    },
                    {
                      "_attributes": {
                        "value": "5",
                        "numvotes": "0"
                      }
                    },
                    {
                      "_attributes": {
                        "value": "6",
                        "numvotes": "0"
                      }
                    },
                    {
                      "_attributes": {
                        "value": "8",
                        "numvotes": "5"
                      }
                    },
                    {
                      "_attributes": {
                        "value": "10",
                        "numvotes": "4"
                      }
                    },
                    {
                      "_attributes": {
                        "value": "12",
                        "numvotes": "0"
                      }
                    },
                    {
                      "_attributes": {
                        "value": "14",
                        "numvotes": "0"
                      }
                    },
                    {
                      "_attributes": {
                        "value": "16",
                        "numvotes": "0"
                      }
                    },
                    {
                      "_attributes": {
                        "value": "18",
                        "numvotes": "0"
                      }
                    },
                    {
                      "_attributes": {
                        "value": "21 and up",
                        "numvotes": "0"
                      }
                    }
                  ]
                }
              ]
            },
            {
              "_attributes": {
                "name": "language_dependence",
                "title": "Language Dependence",
                "totalvotes": "10"
              },
              "results": [
                {
                  "result": [
                    {
                      "_attributes": {
                        "level": "6",
                        "value": "No necessary in-game text",
                        "numvotes": "9"
                      }
                    },
                    {
                      "_attributes": {
                        "level": "7",
                        "value": "Some necessary text - easily memorized or small crib sheet",
                        "numvotes": "1"
                      }
                    },
                    {
                      "_attributes": {
                        "level": "8",
                        "value": "Moderate in-game text - needs crib sheet or paste ups",
                        "numvotes": "0"
                      }
                    },
                    {
                      "_attributes": {
                        "level": "9",
                        "value": "Extensive use of text - massive conversion needed to be playable",
                        "numvotes": "0"
                      }
                    },
                    {
                      "_attributes": {
                        "level": "10",
                        "value": "Unplayable in another language",
                        "numvotes": "0"
                      }
                    }
                  ]
                }
              ]
            }
          ],
          "playingtime": [
            {
              "_attributes": {
                "value": "60"
              }
            }
          ],
          "minplaytime": [
            {
              "_attributes": {
                "value": "30"
              }
            }
          ],
          "maxplaytime": [
            {
              "_attributes": {
                "value": "60"
              }
            }
          ],
          "minage": [
            {
              "_attributes": {
                "value": "8"
              }
            }
          ],
          "link": [
            {
              "_attributes": {
                "type": "boardgamecategory",
                "id": "1042",
                "value": "Expansion for Base-game"
              }
            },
            {
              "_attributes": {
                "type": "boardgamecategory",
                "id": "1034",
                "value": "Trains"
              }
            },
            {
              "_attributes": {
                "type": "boardgamecategory",
                "id": "1011",
                "value": "Transportation"
              }
            },
            {
              "_attributes": {
                "type": "boardgamecategory",
                "id": "1097",
                "value": "Travel"
              }
            },
            {
              "_attributes": {
                "type": "boardgamemechanic",
                "id": "2041",
                "value": "Card Drafting"
              }
            },
            {
              "_attributes": {
                "type": "boardgamemechanic",
                "id": "2040",
                "value": "Hand Management"
              }
            },
            {
              "_attributes": {
                "type": "boardgamemechanic",
                "id": "2081",
                "value": "Route/Network Building"
              }
            },
            {
              "_attributes": {
                "type": "boardgamemechanic",
                "id": "2004",
                "value": "Set Collection"
              }
            },
            {
              "_attributes": {
                "type": "boardgamefamily",
                "id": "10309",
                "value": "Country: The Netherlands"
              }
            },
            {
              "_attributes": {
                "type": "boardgamefamily",
                "id": "17",
                "value": "Ticket to Ride"
              }
            },
            {
              "_attributes": {
                "type": "boardgameexpansion",
                "id": "53383",
                "value": "Ticket to Ride: Europa 1912"
              }
            },
            {
              "_attributes": {
                "type": "boardgameexpansion",
                "id": "9209",
                "value": "Ticket to Ride",
                "inbound": "true"
              }
            },
            {
              "_attributes": {
                "type": "boardgameexpansion",
                "id": "14996",
                "value": "Ticket to Ride: Europe",
                "inbound": "true"
              }
            },
            {
              "_attributes": {
                "type": "boardgameexpansion",
                "id": "21348",
                "value": "Ticket to Ride: Märklin",
                "inbound": "true"
              }
            },
            {
              "_attributes": {
                "type": "boardgameexpansion",
                "id": "119637",
                "value": "Zug um Zug: Deutschland",
                "inbound": "true"
              }
            },
            {
              "_attributes": {
                "type": "boardgamedesigner",
                "id": "9",
                "value": "Alan R. Moon"
              }
            },
            {
              "_attributes": {
                "type": "boardgameartist",
                "id": "12519",
                "value": "Cyrille Daujean"
              }
            },
            {
              "_attributes": {
                "type": "boardgameartist",
                "id": "11886",
                "value": "Julien Delval"
              }
            },
            {
              "_attributes": {
                "type": "boardgamepublisher",
                "id": "1027",
                "value": "Days of Wonder"
              }
            },
            {
              "_attributes": {
                "type": "boardgamepublisher",
                "id": "7466",
                "value": "Rebel"
              }
            }
          ],
          "statistics": [
            {
              "_attributes": {
                "page": "1"
              },
              "ratings": [
                {
                  "usersrated": [
                    {
                      "_attributes": {
                        "value": "1733"
                      }
                    }
                  ],
                  "average": [
                    {
                      "_attributes": {
                        "value": "7.45718"
                      }
                    }
                  ],
                  "bayesaverage": [
                    {
                      "_attributes": {
                        "value": "6.66836"
                      }
                    }
                  ],
                  "ranks": [
                    {
                      "rank": [
                        {
                          "_attributes": {
                            "type": "subtype",
                            "id": "1",
                            "name": "boardgame",
                            "friendlyname": "Board Game Rank",
                            "value": "Not Ranked",
                            "bayesaverage": "6.66836"
                          }
                        },
                        {
                          "_attributes": {
                            "type": "family",
                            "id": "5499",
                            "name": "familygames",
                            "friendlyname": "Family Game Rank",
                            "value": "Not Ranked",
                            "bayesaverage": "6.86789"
                          }
                        }
                      ]
                    }
                  ],
                  "stddev": [
                    {
                      "_attributes": {
                        "value": "1.13554"
                      }
                    }
                  ],
                  "median": [
                    {
                      "_attributes": {
                        "value": "0"
                      }
                    }
                  ],
                  "owned": [
                    {
                      "_attributes": {
                        "value": "5148"
                      }
                    }
                  ],
                  "trading": [
                    {
                      "_attributes": {
                        "value": "46"
                      }
                    }
                  ],
                  "wanting": [
                    {
                      "_attributes": {
                        "value": "236"
                      }
                    }
                  ],
                  "wishing": [
                    {
                      "_attributes": {
                        "value": "710"
                      }
                    }
                  ],
                  "numcomments": [
                    {
                      "_attributes": {
                        "value": "376"
                      }
                    }
                  ],
                  "numweights": [
                    {
                      "_attributes": {
                        "value": "65"
                      }
                    }
                  ],
                  "averageweight": [
                    {
                      "_attributes": {
                        "value": "2.1231"
                      }
                    }
                  ]
                }
              ]
            }
          ]
        }
      ]
    }
  ]
}