{
  "items": [
    {
      "_attributes": {
        "termsofuse": "https://boardgamegeek.com/xmlapi/termsofuse"
      },
      "item": [
        {
          "_attributes": {
            "type": "boardgameexpansion",
            "id": "53383"
          },
          "thumbnail": [
            {
              "_text": [
                "https://cf.geekdo-images.com/thumb/img/BRd7-fbyxEFdKL5stJ1S21ls6Ow=/fit-in/200x150/pic534424.jpg"
              ]
            }
          ],
          "image": [
            {
              "_text": [
                "https://cf.geekdo-images.com/original/img/9Vc76A-B-qgapdx9KAw9Gd3EFQI=/0x0/pic534424.jpg"
              ]
            }
          ],
          "name": [
            {
              "_attributes": {
                "type": "primary",
                "sortindex": "1",
                "value": "Ticket to Ride: Europa 1912"
              }
            },
            {
              "_attributes": {
                "type": "alternate",
                "sortindex": "5",
                "value": "Les Aventuriers du Rail:  Europe 1912"
              }
            },
            {
              "_attributes": {
                "type": "alternate",
                "sortindex": "1",
                "value": "Menolippu: Eurooppa 1912"
              }
            },
            {
              "_attributes": {
                "type": "alternate",
                "sortindex": "1",
                "value": "Ticket to Ride: Европа 1912"
              }
            },
            {
              "_attributes": {
                "type": "alternate",
                "sortindex": "1",
                "value": "Wsiąść do Pociągu: Europa 1912"
              }
            },
            {
              "_attributes": {
                "type": "alternate",
                "sortindex": "1",
                "value": "Wsiąść do Pociągu: Europa 1912"
              }
            },
            {
              "_attributes": {
                "type": "alternate",
                "sortindex": "1",
                "value": "Zug um Zug: Europa 1912"
              }
            },
            {
              "_attributes": {
                "type": "alternate",
                "sortindex": "1",
                "value": "¡Aventureros al Tren! Europa 1912"
              }
            }
          ],
          "description": [
            {
              "_text": [
                "The Ticket to Ride Europa 1912 expansion for the Ticket to Ride series includes 101 Destination Tickets - the 46 original tickets, plus 55 new ones that enable 3 new variants to the Ticket to Ride Europe map: Europe Expanded, which adds 19 new routes to the original 46; Big Cities of Europe, with tickets to 9 major European cities; and Mega Europe, which uses all the new routes as well as the 46 original Destination Tickets.&#10;&#10;This expansion also introduces Warehouses &amp; Depots - new game rules and pieces that create an additional strategic layer and can be played with any of the Ticket to Ride maps. Wooden Train Depots are placed on cities selected by each player. Throughout the game, each player's Warehouse will accumulate Train cards and those who have the foresight, clever timing, or just plain good fortune to build a route to a Depot can make off with a fistful of Train cards. Depot placement and skillful Warehouse tactics become a key part of a winning Ticket to Ride strategy!&#10;&#10;Part of Ticket to Ride series.&#10;&#10;"
              ]
            }
          ],
          "yearpublished": [
            {
              "_attributes": {
                "value": "2009"
              }
            }
          ],
          "minplayers": [
            {
              "_attributes": {
                "value": "2"
              }
            }
          ],
          "maxplayers": [
            {
              "_attributes": {
                "value": "5"
              }
            }
          ],
          "poll": [
            {
              "_attributes": {
                "name": "suggested_numplayers",
                "title": "User Suggested Number of Players",
                "totalvotes": "25"
              },
              "results": [
                {
                  "_attributes": {
                    "numplayers": "1"
                  },
                  "result": [
                    {
                      "_attributes": {
                        "value": "Best",
                        "numvotes": "0"
                      }
                    },
                    {
                      "_attributes": {
                        "value": "Recommended",
                        "numvotes": "0"
                      }
                    },
                    {
                      "_attributes": {
                        "value": "Not Recommended",
                        "numvotes": "21"
                      }
                    }
                  ]
                },
                {
                  "_attributes": {
                    "numplayers": "2"
                  },
                  "result": [
                    {
                      "_attributes": {
                        "value": "Best",
                        "numvotes": "2"
                      }
                    },
                    {
                      "_attributes": {
                        "value": "Recommended",
                        "numvotes": "16"
                      }
                    },
                    {
                      "_attributes": {
                        "value": "Not Recommended",
                        "numvotes": "7"
                      }
                    }
                  ]
                },
                {
                  "_attributes": {
                    "numplayers": "3"
                  },
                  "result": [
                    {
                      "_attributes": {
                        "value": "Best",
                        "numvotes": "5"
                      }
                    },
                    {
                      "_attributes": {
                        "value": "Recommended",
                        "numvotes": "19"
                      }
                    },
                    {
                      "_attributes": {
                        "value": "Not Recommended",
                        "numvotes": "1"
                      }
                    }
                  ]
                },
                {
                  "_attributes": {
                    "numplayers": "4"
                  },
                  "result": [
                    {
                      "_attributes": {
                        "value": "Best",
                        "numvotes": "20"
                      }
                    },
                    {
                      "_attributes": {
                        "value": "Recommended",
                        "numvotes": "4"
                      }
                    },
                    {
                      "_attributes": {
                        "value": "Not Recommended",
                        "numvotes": "1"
                      }
                    }
                  ]
                },
                {
                  "_attributes": {
                    "numplayers": "5"
                  },
                  "result": [
                    {
                      "_attributes": {
                        "value": "Best",
                        "numvotes": "12"
                      }
                    },
                    {
                      "_attributes": {
                        "value": "Recommended",
                        "numvotes": "12"
                      }
                    },
                    {
                      "_attributes": {
                        "value": "Not Recommended",
                        "numvotes": "1"
                      }
                    }
                  ]
                },
                {
                  "_attributes": {
                    "numplayers": "5+"
                  },
                  "result": [
                    {
                      "_attributes": {
                        "value": "Best",
                        "numvotes": "0"
                      }
                    },
                    {
                      "_attributes": {
                        "value": "Recommended",
                        "numvotes": "0"
                      }
                    },
                    {
                      "_attributes": {
                        "value": "Not Recommended",
                        "numvotes": "20"
                      }
                    }
                  ]
                }
              ]
            },
            {
              "_attributes": {
                "name": "suggested_playerage",
                "title": "User Suggested Player Age",
                "totalvotes": "9"
              },
              "results": [
                {
                  "result": [
                    {
                      "_attributes": {
                        "value": "2",
                        "numvotes": "0"
                      }
                    },
                    {
                      "_attributes": {
                        "value": "3",
                        "numvotes": "0"
                      }
                    },
                    {
                      "_attributes": {
                        "value": "4",
                        "numvotes": "0"
                      }
                    },
                    {
                      "_attributes": {
                        "value": "5",
                        "numvotes": "0"
                      }
                    },
                    {
                      "_attributes": {
                        "value": "6",
                        "numvotes": "0"
                      }
                    },
                    {
                      "_attributes": {
                        "value": "8",
                        "numvotes": "7"
                      }
                    },
                    {
                      "_attributes": {
                        "value": "10",
                        "numvotes": "2"
                      }
                    },
                    {
                      "_attributes": {
                        "value": "12",
                        "numvotes": "0"
                      }
                    },
                    {
                      "_attributes": {
                        "value": "14",
                        "numvotes": "0"
                      }
                    },
                    {
                      "_attributes": {
                        "value": "16",
                        "numvotes": "0"
                      }
                    },
                    {
                      "_attributes": {
                        "value": "18",
                        "numvotes": "0"
                      }
                    },
                    {
                      "_attributes": {
                        "value": "21 and up",
                        "numvotes": "0"
                      }
                    }
                  ]
                }
              ]
            },
            {
              "_attributes": {
                "name": "language_dependence",
                "title": "Language Dependence",
                "totalvotes": "15"
              },
              "results": [
                {
                  "result": [
                    {
                      "_attributes": {
                        "level": "11",
                        "value": "No necessary in-game text",
                        "numvotes": "15"
                      }
                    },
                    {
                      "_attributes": {
                        "level": "12",
                        "value": "Some necessary text - easily memorized or small crib sheet",
                        "numvotes": "0"
                      }
                    },
                    {
                      "_attributes": {
                        "level": "13",
                        "value": "Moderate in-game text - needs crib sheet or paste ups",
                        "numvotes": "0"
                      }
                    },
                    {
                      "_attributes": {
                        "level": "14",
                        "value": "Extensive use of text - massive conversion needed to be playable",
                        "numvotes": "0"
                      }
                    },
                    {
                      "_attributes": {
                        "level": "15",
                        "value": "Unplayable in another language",
                        "numvotes": "0"
                      }
                    }
                  ]
                }
              ]
            }
          ],
          "playingtime": [
            {
              "_attributes": {
                "value": "60"
              }
            }
          ],
          "minplaytime": [
            {
              "_attributes": {
                "value": "30"
              }
            }
          ],
          "maxplaytime": [
            {
              "_attributes": {
                "value": "60"
              }
            }
          ],
          "minage": [
            {
              "_attributes": {
                "value": "8"
              }
            }
          ],
          "link": [
            {
              "_attributes": {
                "type": "boardgamecategory",
                "id": "1042",
                "value": "Expansion for Base-game"
              }
            },
            {
              "_attributes": {
                "type": "boardgamecategory",
                "id": "1034",
                "value": "Trains"
              }
            },
            {
              "_attributes": {
                "type": "boardgamemechanic",
                "id": "2041",
                "value": "Card Drafting"
              }
            },
            {
              "_attributes": {
                "type": "boardgamemechanic",
                "id": "2040",
                "value": "Hand Management"
              }
            },
            {
              "_attributes": {
                "type": "boardgamemechanic",
                "id": "2081",
                "value": "Route/Network Building"
              }
            },
            {
              "_attributes": {
                "type": "boardgamemechanic",
                "id": "2004",
                "value": "Set Collection"
              }
            },
            {
              "_attributes": {
                "type": "boardgamefamily",
                "id": "50153",
                "value": "Continent: Europe"
              }
            },
            {
              "_attributes": {
                "type": "boardgamefamily",
                "id": "17",
                "value": "Ticket to Ride"
              }
            },
            {
              "_attributes": {
                "type": "boardgameexpansion",
                "id": "9209",
                "value": "Ticket to Ride",
                "inbound": "true"
              }
            },
            {
              "_attributes": {
                "type": "boardgameexpansion",
                "id": "106637",
                "value": "Ticket to Ride Map Collection: Volume 1 – Team Asia & Legendary Asia",
                "inbound": "true"
              }
            },
            {
              "_attributes": {
                "type": "boardgameexpansion",
                "id": "106645",
                "value": "Ticket to Ride Map Collection: Volume 2 – India & Switzerland",
                "inbound": "true"
              }
            },
            {
              "_attributes": {
                "type": "boardgameexpansion",
                "id": "131188",
                "value": "Ticket to Ride Map Collection: Volume 3 – The Heart of Africa",
                "inbound": "true"
              }
            },
            {
              "_attributes": {
                "type": "boardgameexpansion",
                "id": "147938",
                "value": "Ticket to Ride Map Collection: Volume 4 – Nederland",
                "inbound": "true"
              }
            },
            {
              "_attributes": {
                "type": "boardgameexpansion",
                "id": "182078",
                "value": "Ticket to Ride Map Collection: Volume 5 – United Kingdom & Pennsylvania",
                "inbound": "true"
              }
            },
            {
              "_attributes": {
                "type": "boardgameexpansion",
                "id": "14996",
                "value": "Ticket to Ride: Europe",
                "inbound": "true"
              }
            },
            {
              "_attributes": {
                "type": "boardgameexpansion",
                "id": "21348",
                "value": "Ticket to Ride: Märklin",
                "inbound": "true"
              }
            },
            {
              "_attributes": {
                "type": "boardgameexpansion",
                "id": "31627",
                "value": "Ticket to Ride: Nordic Countries",
                "inbound": "true"
              }
            },
            {
              "_attributes": {
                "type": "boardgameexpansion",
                "id": "202670",
                "value": "Ticket to Ride: Rails & Sails",
                "inbound": "true"
              }
            },
            {
              "_attributes": {
                "type": "boardgameexpansion",
                "id": "30746",
                "value": "Ticket to Ride: Switzerland",
                "inbound": "true"
              }
            },
            {
              "_attributes": {
                "type": "boardgameexpansion",
                "id": "119637",
                "value": "Zug um Zug: Deutschland",
                "inbound": "true"
              }
            },
            {
              "_attributes": {
                "type": "boardgamedesigner",
                "id": "9",
                "value": "Alan R. Moon"
              }
            },
            {
              "_attributes": {
                "type": "boardgameartist",
                "id": "12519",
                "value": "Cyrille Daujean"
              }
            },
            {
              "_attributes": {
                "type": "boardgameartist",
                "id": "11886",
                "value": "Julien Delval"
              }
            },
            {
              "_attributes": {
                "type": "boardgamepublisher",
                "id": "1027",
                "value": "Days of Wonder"
              }
            },
            {
              "_attributes": {
                "type": "boardgamepublisher",
                "id": "18852",
                "value": "Hobby World"
              }
            },
            {
              "_attributes": {
                "type": "boardgamepublisher",
                "id": "3218",
                "value": "Lautapelit.fi"
              }
            },
            {
              "_attributes": {
                "type": "boardgamepublisher",
                "id": "7466",
                "value": "Rebel"
              }
            }
          ],
          "statistics": [
            {
              "_attributes": {
                "page": "1"
              },
              "ratings": [
                {
                  "usersrated": [
                    {
                      "_attributes": {
                        "value": "3730"
                      }
                    }
                  ],
                  "average": [
                    {
                      "_attributes": {
                        "value": "7.65397"
                      }
                    }
                  ],
                  "bayesaverage": [
                    {
                      "_attributes": {
                        "value": "7.1061"
                      }
                    }
                  ],
                  "ranks": [
                    {
                      "rank": [
                        {
                          "_attributes": {
                            "type": "subtype",
                            "id": "1",
                            "name": "boardgame",
                            "friendlyname": "Board Game Rank",
                            "value": "Not Ranked",
                            "bayesaverage": "7.1061"
                          }
                        },
                        {
                          "_attributes": {
                            "type": "family",
                            "id": "5499",
                            "name": "familygames",
                            "friendlyname": "Family Game Rank",
                            "value": "Not Ranked",
                            "bayesaverage": "7.25675"
                          }
                        }
                      ]
                    }
                  ],
                  "stddev": [
                    {
                      "_attributes": {
                        "value": "1.16437"
                      }
                    }
                  ],
                  "median": [
                    {
                      "_attributes": {
                        "value": "0"
                      }
                    }
                  ],
                  "owned": [
                    {
                      "_attributes": {
                        "value": "11571"
                      }
                    }
                  ],
                  "trading": [
                    {
                      "_attributes": {
                        "value": "65"
                      }
                    }
                  ],
                  "wanting": [
                    {
                      "_attributes": {
                        "value": "188"
                      }
                    }
                  ],
                  "wishing": [
                    {
                      "_attributes": {
                        "value": "828"
                      }
                    }
                  ],
                  "numcomments": [
                    {
                      "_attributes": {
                        "value": "884"
                      }
                    }
                  ],
                  "numweights": [
                    {
                      "_attributes": {
                        "value": "212"
                      }
                    }
                  ],
                  "averageweight": [
                    {
                      "_attributes": {
                        "value": "1.9481"
                      }
                    }
                  ]
                }
              ]
            }
          ]
        }
      ]
    }
  ]
}