{
  "boardGameGeekGameId": "207370",
  "boardGameGeekName": "Design Town",
  "boardGameApiId": "design-town",
  "name": "Design Town",
  "playRecords": [
    {
      "date": "2020-03-18",
      "winner": "Hannah",
      "coOp": "No",
      "gameFamily": "Design Town",
      "source": "gsheets://1FyeEeWPKch4jVoBoD_lB89GbsUPkYTESkfIeknUhyJw/2020/18"
    },
    {
      "date": "2020-03-19",
      "winner": "Hannah",
      "coOp": "No",
      "gameFamily": "Design Town",
      "source": "gsheets://1FyeEeWPKch4jVoBoD_lB89GbsUPkYTESkfIeknUhyJw/2020/25"
    },
    {
      "date": "2020-03-24",
      "winner": "Hannah",
      "coOp": "No",
      "gameFamily": "Design Town",
      "source": "gsheets://1FyeEeWPKch4jVoBoD_lB89GbsUPkYTESkfIeknUhyJw/2020/33"
    },
    {
      "date": "2020-05-18",
      "winner": "John",
      "coOp": "No",
      "gameFamily": "Design Town",
      "source": "gsheets://1FyeEeWPKch4jVoBoD_lB89GbsUPkYTESkfIeknUhyJw/2020/16"
    },
    {
      "date": "2020-08-23",
      "winner": "John",
      "coOp": "No",
      "gameFamily": "Design Town",
      "source": "gsheets://1FyeEeWPKch4jVoBoD_lB89GbsUPkYTESkfIeknUhyJw/2020/26"
    },
    {
      "date": "2021-01-02",
      "winner": "John",
      "coOp": "No",
      "gameFamily": "Design Town",
      "source": "gsheets://1Va-06sfmVq-UFBxWwo6U5v6N9W_lizW5GvgyogQdGQQ/2021/7"
    },
    {
      "date": "2021-01-30",
      "winner": "John",
      "coOp": "No",
      "gameFamily": "Design Town",
      "source": "gsheets://1Va-06sfmVq-UFBxWwo6U5v6N9W_lizW5GvgyogQdGQQ/2021/49"
    },
    {
      "date": "2021-02-13",
      "winner": "Hannah",
      "coOp": "No",
      "gameFamily": "Design Town ",
      "source": "gsheets://1Va-06sfmVq-UFBxWwo6U5v6N9W_lizW5GvgyogQdGQQ/2021/19"
    },
    {
      "date": "2021-03-06",
      "winner": "Hannah ",
      "coOp": "No",
      "gameFamily": "Design Town ",
      "source": "gsheets://1Va-06sfmVq-UFBxWwo6U5v6N9W_lizW5GvgyogQdGQQ/2021/1"
    },
    {
      "date": "2021-03-09",
      "winner": "John",
      "coOp": "No",
      "gameFamily": "Design Town ",
      "source": "gsheets://1Va-06sfmVq-UFBxWwo6U5v6N9W_lizW5GvgyogQdGQQ/2021/12"
    },
    {
      "date": "2021-04-02",
      "winner": "Hannah",
      "coOp": "No",
      "gameFamily": "Design Town",
      "source": "gsheets://1Va-06sfmVq-UFBxWwo6U5v6N9W_lizW5GvgyogQdGQQ/2021/1"
    },
    {
      "date": "2021-10-14",
      "winner": "Hannah",
      "coOp": "No",
      "gameFamily": "Design Town ",
      "source": "gsheets://1Va-06sfmVq-UFBxWwo6U5v6N9W_lizW5GvgyogQdGQQ/2021/14"
    },
    {
      "date": "2021-11-05",
      "winner": "Hannah",
      "coOp": "No",
      "source": "gsheets://1Va-06sfmVq-UFBxWwo6U5v6N9W_lizW5GvgyogQdGQQ/2021/0"
    },
    {
      "date": "2021-11-06",
      "winner": "Hannah",
      "coOp": "No",
      "source": "gsheets://1Va-06sfmVq-UFBxWwo6U5v6N9W_lizW5GvgyogQdGQQ/2021/1"
    },
    {
      "date": "2021-11-23",
      "winner": "Hannah",
      "coOp": "No",
      "source": "gsheets://1Va-06sfmVq-UFBxWwo6U5v6N9W_lizW5GvgyogQdGQQ/2021/18"
    },
    {
      "date": "2022-06-04",
      "winner": "Hannah",
      "coOp": "no",
      "notes": "At UKGE",
      "noOfPlayers": 2,
      "source": "s3://boardgames-api-playrecords-prod/original/2022/06/2022-06-20T20:04:23.725Z.json"
    },
    {
      "date": "2022-07-23",
      "winner": "Hannah",
      "coOp": "no",
      "noOfPlayers": 2,
      "source": "s3://boardgames-api-playrecords-prod/original/2022/07/2022-07-30T13:00:39.472Z.json"
    },
    {
      "date": "2023-01-30",
      "winner": "Hannah",
      "coOp": "no",
      "noOfPlayers": 2,
      "source": "s3://boardgames-api-playrecords-prod/original/2023/01/2023-01-31T14:37:42.955Z.json"
    },
    {
      "date": "2023-02-28",
      "winner": "Hannah",
      "coOp": "no",
      "noOfPlayers": 2,
      "source": "s3://boardgames-api-playrecords-prod/original/2023/02/2023-02-28T19:29:50.353Z.json"
    },
    {
      "date": "2023-04-28",
      "winner": "Hannah",
      "coOp": "no",
      "noOfPlayers": 2,
      "source": "s3://boardgames-api-playrecords-prod/original/2023/05/2023-05-04T10:37:19.955Z.json"
    },
    {
      "date": "2023-07-04",
      "winner": "Hannah",
      "coOp": "no",
      "noOfPlayers": 2,
      "source": "s3://boardgames-api-playrecords-prod/original/2023/07/2023-07-12T17:03:08.883Z.json"
    },
    {
      "date": "2023-09-26",
      "winner": "John",
      "coOp": "no",
      "noOfPlayers": 2,
      "source": "s3://boardgames-api-playrecords-prod/original/2023/09/2023-09-26T14:12:34.800Z.json"
    },
    {
      "date": "2023-11-15",
      "winner": "Hannah",
      "coOp": "no",
      "noOfPlayers": 2,
      "source": "s3://boardgames-api-playrecords-prod/playrecords/2023/11/2023-11-19T08:56:22.929Z.json"
    }
  ],
  "totalGamesPlayed": 23,
  "coOpGamesPlayedCount": 0,
  "coOpGamesPlayedPercentage": 0,
  "coOpGameWins": 0,
  "coOpGameLoses": 0,
  "coOpWinRate": 0,
  "coOpLossRate": 0,
  "winCountHannah": 16,
  "winCountJohn": 6,
  "winCountOther": 0,
  "winCountDraw": 0,
  "winnableGamesTotal": 22,
  "winPercentageHannah": 0.7273,
  "winPercentageJohn": 0.2727,
  "winPercentageOther": 0,
  "winPercentageDraw": 0,
  "mostWonGames": "Hannah"
}