{
  "boardGameApiId": "dominion",
  "playRecords": [
    {
      "date": "2020-01-05",
      "winner": "Hannah",
      "coOp": "No",
      "gameFamily": "Dominion",
      "source": "gsheets://1FyeEeWPKch4jVoBoD_lB89GbsUPkYTESkfIeknUhyJw/2020/5"
    },
    {
      "date": "2020-04-02",
      "winner": "John",
      "coOp": "No",
      "gameFamily": "Dominion",
      "source": "gsheets://1FyeEeWPKch4jVoBoD_lB89GbsUPkYTESkfIeknUhyJw/2020/1"
    },
    {
      "date": "2020-07-18",
      "winner": "John",
      "coOp": "No",
      "gameFamily": "Dominion",
      "source": "gsheets://1FyeEeWPKch4jVoBoD_lB89GbsUPkYTESkfIeknUhyJw/2020/19"
    },
    {
      "date": "2021-01-02",
      "winner": "John",
      "coOp": "No",
      "gameFamily": "Dominion",
      "source": "gsheets://1Va-06sfmVq-UFBxWwo6U5v6N9W_lizW5GvgyogQdGQQ/2021/9"
    },
    {
      "date": "2021-02-01",
      "winner": "John",
      "coOp": "No",
      "gameFamily": "Dominion",
      "source": "gsheets://1Va-06sfmVq-UFBxWwo6U5v6N9W_lizW5GvgyogQdGQQ/2021/0"
    },
    {
      "date": "2021-02-01",
      "winner": "Hannah",
      "coOp": "No",
      "gameFamily": "Dominion",
      "source": "gsheets://1Va-06sfmVq-UFBxWwo6U5v6N9W_lizW5GvgyogQdGQQ/2021/1"
    },
    {
      "date": "2023-04-21",
      "winner": "John",
      "coOp": "no",
      "noOfPlayers": 2,
      "expansions": [
        "Dominion: Prosperity"
      ],
      "source": "s3://boardgames-api-playrecords-prod/original/2023/05/2023-05-04T10:34:52.053Z.json"
    },
    {
      "date": "2023-04-22",
      "winner": "John",
      "coOp": "no",
      "noOfPlayers": 2,
      "expansions": [
        "Dominion: Prosperity"
      ],
      "source": "s3://boardgames-api-playrecords-prod/original/2023/05/2023-05-04T10:35:08.009Z.json"
    },
    {
      "date": "2023-04-23",
      "winner": "Hannah",
      "coOp": "no",
      "noOfPlayers": 2,
      "expansions": [
        "Dominion: Prosperity"
      ],
      "source": "s3://boardgames-api-playrecords-prod/original/2023/05/2023-05-04T10:35:17.180Z.json"
    },
    {
      "date": "2023-04-23",
      "winner": "Hannah",
      "coOp": "no",
      "noOfPlayers": 2,
      "expansions": [
        "Dominion: Prosperity"
      ],
      "source": "s3://boardgames-api-playrecords-prod/original/2023/05/2023-05-04T10:35:20.772Z.json"
    },
    {
      "date": "2023-04-24",
      "winner": "John",
      "coOp": "no",
      "noOfPlayers": 2,
      "expansions": [
        "Dominion: Prosperity"
      ],
      "source": "s3://boardgames-api-playrecords-prod/original/2023/05/2023-05-04T10:35:30.873Z.json"
    }
  ],
  "name": "Dominion",
  "totalGamesPlayed": 11,
  "coOpGamesPlayedCount": 0,
  "coOpGamesPlayedPercentage": 0,
  "coOpGameWins": 0,
  "coOpGameLoses": 0,
  "coOpWinRate": 0,
  "coOpLossRate": 0,
  "winCountHannah": 4,
  "winCountJohn": 7,
  "winCountOther": 0,
  "winCountDraw": 0,
  "winnableGamesTotal": 11,
  "winPercentageHannah": 0.3636,
  "winPercentageJohn": 0.6364,
  "winPercentageOther": 0,
  "winPercentageDraw": 0,
  "mostWonGames": "John"
}