{
  "boardGameGeekGameId": "65244",
  "boardGameGeekName": "Forbidden Island",
  "boardGameApiId": "forbidden-island",
  "name": "Forbidden Island",
  "playRecords": [
    {
      "date": "2018-05-28",
      "coOp": "Yes"
    },
    {
      "date": "2018-08-11",
      "coOpOutcome": "Won",
      "coOp": "Yes"
    },
    {
      "date": "2020-04-03",
      "coOpOutcome": "Won",
      "coOp": "Yes"
    }
  ],
  "totalGamesPlayed": 3,
  "coOpGamesPlayedCount": 3,
  "coOpGamesPlayedPercentage": 1,
  "coOpGameWins": 2,
  "coOpGameLoses": 1,
  "coOpWinRate": 0.6667,
  "coOpLossRate": 0.3333,
  "winCountHannah": 0,
  "winCountJohn": 0,
  "winCountOther": 0,
  "winCountDraw": 0,
  "winnableGamesTotal": 0,
  "winPercentageHannah": 0,
  "winPercentageJohn": 0,
  "winPercentageOther": 0,
  "winPercentageDraw": 0,
  "mostWonGames": "Draw"
}