{
  "boardGameApiId": "mint-cooperative",
  "playRecords": [
    {
      "date": "2022-01-05",
      "coOpOutcome": "win",
      "coOp": "yes",
      "noOfPlayers": 2,
      "source": "s3://boardgames-api-playrecords-prod/original/2022/01/2022-01-07T14:49:14.368Z.json"
    }
  ],
  "name": "Mint Cooperative",
  "totalGamesPlayed": 1,
  "coOpGamesPlayedCount": 1,
  "coOpGamesPlayedPercentage": 1,
  "coOpGameWins": 1,
  "coOpGameLoses": 0,
  "coOpWinRate": 1,
  "coOpLossRate": 0,
  "winCountHannah": 0,
  "winCountJohn": 0,
  "winCountOther": 0,
  "winCountDraw": 0,
  "winnableGamesTotal": 0,
  "winPercentageHannah": 0,
  "winPercentageJohn": 0,
  "winPercentageOther": 0,
  "winPercentageDraw": 0,
  "mostWonGames": "Draw"
}